README.md
setup.py
reactive/actor/__init__.py
reactive/actor/base_actor.py
reactive/actor/name_creation_utils.py
reactive/actor/routee.py
reactive/actor/state.py
reactive/actor_system/__init__.py
reactive/actor_system/system_type.py
reactive/error/__init__.py
reactive/error/handler.py
reactive/errors/__init__.py
reactive/errors/streams.py
reactive/failure/__init__.py
reactive/failure/restart_strategy.py
reactive/message/__init__.py
reactive/message/base_message.py
reactive/message/failure_handling.py
reactive/message/rabbit_messages.py
reactive/message/router_messages.py
reactive/message/stream_messages.py
reactive/message/stream_priority_messages.py
reactive/message/stream_publisher_messages.py
reactive/message/stream_sink_messages.py
reactive/message/stream_sub_pool_messages.py
reactive/message/stream_work_stage_messages.py
reactive/message/troupe_messages.py
reactive/message/worker_messages.py
reactive/routers/__init__.py
reactive/routers/pub_sub.py
reactive/routers/random.py
reactive/routers/round_robin.py
reactive/routers/router_type.py
reactive/streams/__init__.py
reactive/streams/actors/__init__.py
reactive/streams/actors/sink.py
reactive/streams/actors/transient.py
reactive/streams/actors/troupe.py
reactive/streams/base_objects/__init__.py
reactive/streams/base_objects/balancing_publisher.py
reactive/streams/base_objects/logic_publisher.py
reactive/streams/base_objects/multi_queue_publisher.py
reactive/streams/base_objects/priority_subscription_pool.py
reactive/streams/base_objects/publisher.py
reactive/streams/base_objects/rated_subscription_pool.py
reactive/streams/base_objects/round_robin_subscription_pool.py
reactive/streams/base_objects/subscription.py
reactive/streams/base_objects/subscription_pool.py
reactive/streams/base_objects/supervisor.py
reactive/streams/enums/__init__.py
reactive/streams/enums/publisher_type.py
reactive/streams/enums/subscriber_type.py
reactive/streams/manager/__init__.py
reactive/streams/manager/graph_builder.py
thespian_reactive.egg-info/PKG-INFO
thespian_reactive.egg-info/SOURCES.txt
thespian_reactive.egg-info/dependency_links.txt
thespian_reactive.egg-info/requires.txt
thespian_reactive.egg-info/top_level.txt