Metadata-Version: 1.2
Name: thespian-reactive
Version: 0.1a0
Summary: Reactive Streams for Python
Home-page: UNKNOWN
Author: Andrew Evans
Author-email: aevans48@simplrinsites.com
License: Apache License 2.0
Keywords: reactive thespian actor etl stream
Platform: UNKNOWN
Classifier: Development Status :: 3 - Alpha
Classifier: Programming Language :: Python :: 3.5
Classifier: Programming Language :: Python :: 3.6
Requires-Python: ~=3.5
